{
  "id": "us-catonsville-md",
  "name": "Catonsville MD, USA",
  "country": "United States",
  "region": "Maryland",
  "cities": ["Catonsville", "Oella", "Arbutus"],
  "currency": "USD",
  "exchangeRate": 1,
  "visa": { "type": "Citizen", "incomeRequirement": null, "notes": "US citizen, no visa required." },
  "climate": { "winterLowF": 25, "summerHighF": 88, "rainyDaysPerYear": 114, "meetsWarmWinterReq": false },
  "monthlyCosts": {
    "rent": { "min": 1750, "max": 2450, "typical": 2050, "type": "2-bedroom older SFH / townhome", "annualInflation": 0.035, "notes": "Baltimore County — mature tree-lined neighborhoods along Frederick Road corridor, historic Oella (mill village) to south. UMBC (University of Maryland, Baltimore County) + Catonsville Community College keep area vibrant." },
    "groceries": { "min": 1270, "max": 1670, "typical": 1445, "annualInflation": 0.03, "notes": "Wegmans, Giant, Harris Teeter, Trader Joe's, H Mart (Korean). Strong grocery variety for the price point." },
    "utilities": { "min": 255, "max": 415, "typical": 330, "annualInflation": 0.03, "notes": "BGE electric + Washington Gas + Baltimore County DPW water/sewer." },
    "healthcare": { "min": 540, "max": 830, "typical": 640, "notes": "Medicare baseline. UM St. Agnes Hospital 5 min, Johns Hopkins campus 15 min, UM Medical Center (Baltimore) 15 min. Exceptional specialist density.", "annualInflation": 0.055 },
    "insurance": { "min": 35, "max": 55, "typical": 45, "type": "renter's insurance", "annualInflation": 0.03 },
    "petCare": { "min": 125, "max": 225, "typical": 165, "annualInflation": 0.04 },
    "petDaycare": { "min": 300, "max": 475, "typical": 385, "annualInflation": 0.035 },
    "petGrooming": { "min": 85, "max": 155, "typical": 115, "annualInflation": 0.03 },
    "transportation": { "min": 275, "max": 510, "typical": 390, "annualInflation": 0.03, "notes": "MTA (Maryland Transit Administration) bus to Baltimore. Light Rail 15 min (via car). Interstate 95/Interstate 695 access. BWI (Baltimore-Washington International airport) 20 min. No direct MARC station; Penn Line at Baltimore Penn Station 15 min." },
    "entertainment": { "min": 415, "max": 605, "typical": 500, "annualInflation": 0.025, "notes": "Walkable Frederick Road commercial strip, Patapsco Valley State Park trails, UMBC (University of Maryland, Baltimore County) events + Fine Arts shows, Catonsville Arts District. Cable+1Gig typical." },
    "clothing": { "min": 95, "max": 230, "typical": 150, "annualInflation": 0.02 },
    "personalCare": { "min": 45, "max": 105, "typical": 68, "annualInflation": 0.02 },
    "subscriptions": { "min": 30, "max": 80, "typical": 55, "annualInflation": 0.03 },
    "phoneCell": { "min": 50, "max": 80, "typical": 62, "annualInflation": 0.02 },
    "miscellaneous": { "min": 110, "max": 225, "typical": 160, "annualInflation": 0.025, "notes": "Fewer HOAs (homeowners associations) than newer MD suburbs. Interstate 95 + ICC (Intercounty Connector toll road) tolls. Baltimore County piggyback 3.20%." },
    "buffer": { "min": 750, "max": 750, "typical": 750, "annualInflation": 0.025 },
    "medicalOOP": { "min": 325, "max": 700, "typical": 475, "annualInflation": 0.055, "notes": "Same retiree profile. World-class specialist access: UM St. Agnes in town, Johns Hopkins + UM Medical Center 15 min. One of the best healthcare locations for complex retirees." },
    "medicine": { "min": 73, "typical": 91, "max": 925, "annualInflation": 0.045 },
    "taxes": { "typical": 0, "min": 0, "max": 0, "annualInflation": 0.02, "notes": "Income tax computed from MD + Baltimore County brackets." },
    "healthcarePreMedicare": { "min": 1700, "max": 2600, "typical": 2100, "annualInflation": 0.06, "notes": "ACA silver benchmark for 2-adult household both age ~60, before subsidies. County-level estimate (Baltimore County, MD). Maryland Health Connection — Baltimore metro competitive marketplace. Estimated ±15% vs healthcare.gov quote — verify for a specific ZIP before relying on the number." }
  },
  "taxes": {
    "federalIncomeTax": {
      "applies": true,
      "brackets": [
        { "min": 0, "max": 23850, "rate": 0.10 }, { "min": 23850, "max": 96950, "rate": 0.12 },
        { "min": 96950, "max": 206700, "rate": 0.22 }, { "min": 206700, "max": 394600, "rate": 0.24 },
        { "min": 394600, "max": 501050, "rate": 0.32 }, { "min": 501050, "max": 751600, "rate": 0.35 },
        { "min": 751600, "max": null, "rate": 0.37 }
      ],
      "standardDeduction": 30000
    },
    "stateIncomeTax": {
      "rate": 0.0795, "type": "combined-state-plus-county",
      "brackets": [
        { "min": 0, "max": 1000, "rate": 0.0520 },
        { "min": 1000, "max": 2000, "rate": 0.0620 },
        { "min": 2000, "max": 3000, "rate": 0.0720 },
        { "min": 3000, "max": 100000, "rate": 0.0795 },
        { "min": 100000, "max": 125000, "rate": 0.0820 },
        { "min": 125000, "max": 150000, "rate": 0.0845 },
        { "min": 150000, "max": 250000, "rate": 0.0870 },
        { "min": 250000, "max": null, "rate": 0.0895 }
      ],
      "deduction": 5150,
      "exemptions": "MD pension exclusion up to ~$39K for retirees 65+; SS fully exempt. Combined MD state + Baltimore County piggyback (3.20%)."
    },
    "salesTax": { "rate": 0.06, "notes": "Maryland statewide 6%; no local add-ons." },
    "propertyTax": { "rate": 0, "notes": "Renters: no direct property tax. Maryland has no vehicle personal property tax." },
    "socialCharges": null,
    "vatRate": 0,
    "estVehicleTax": 0,
    "ssExempt": true,
    "notes": "MD tax benefits (Social Security exempt, pension exclusion, no vehicle tax). Baltimore County piggyback 3.20%."
  },
  "healthcare": {
    "system": "Medicare (at 65) + private supplement",
    "qualityRating": 9, "waitTimes": "low", "dentalIncluded": false, "prescriptionCoverage": "Part D plan",
    "notes": "Outstanding healthcare density: UM St. Agnes Hospital in town (5 min), Johns Hopkins Bayview + Hopkins main campus 15-20 min, UM Medical Center (Baltimore) 15 min, GBMC 20 min. Excellent for complex retiree medical needs.",
    "acaMarketplace": {
      "benchmarkSilverMonthly2Adult": 2100, "benchmarkSilverMonthlySingle": 1050,
      "premiumCapPctOfIncome": 0.085, "rateArea": "Baltimore County",
      "notes": "Maryland Health Connection — Baltimore County rating area (competitive metro marketplace).",
      "estimationLevel": "county", "disclaimer": "Estimated ±15% vs healthcare.gov quote — verify for a specific ZIP before relying on the number."
    }
  },
  "lifestyle": {
    "internetSpeed": "1Gbps widely available (Comcast/Xfinity)",
    "dogFriendly": 9, "expatCommunity": 4, "englishPrevalence": 10, "safetyRating": 8,
    "notes": "Walkable Frederick Road commercial district with local restaurants, breweries, and the historic Catonsville Lumber. Patapsco Valley State Park trails literally in town. UMBC (University of Maryland, Baltimore County) campus cultural events. Strong schools and mature tree-lined neighborhoods. Historic Oella mill village walkable from downtown."
  },
  "pros": [
    "~$2,500/mo cheaper than Fairfax while keeping walkable-town character",
    "MD tax benefits: Social Security exempt, pension exclusion, no vehicle property tax",
    "World-class healthcare (St. Agnes in town, Johns Hopkins + UM 15 min)",
    "Walkable Frederick Road commercial strip — real pedestrian life",
    "Patapsco Valley State Park trails in town",
    "UMBC (University of Maryland, Baltimore County) campus = cultural events, continuing education, Fine Arts",
    "Mature tree-lined neighborhoods, less strip-mall feel than outer MD suburbs",
    "Diverse community"
  ],
  "cons": [
    "Baltimore County piggyback 3.20% — tied for highest in MD",
    "No direct MARC station (15 min to Penn Station)",
    "~55 mi from Fairfax — longer drive than Bowie",
    "Not on the water (unlike Annapolis)",
    "Some older housing requires maintenance",
    "Baltimore metro reputation concerns (though Catonsville itself is safe)"
  ]
}
