{
  "officialSites": [
    {
      "name": "Municipalidad de San Carlos",
      "url": "https://www.munisc.go.cr/",
      "type": "government",
      "scope": "municipio",
      "linkStatus": "ok",
      "linkHttpStatus": 200,
      "linkCheckedAt": "2026-04-23"
    }
  ],
  "webcams": [
    {
      "name": "Arenal / Lake Arenal webcams (search)",
      "url": "https://www.windy.com/-Webcams/webcams?Arenal%20%2F%20Lake%20Arenal%20webcam",
      "description": "Live webcams near Arenal / Lake Arenal — Windy directory, rating-sorted. Replace with a specific camera once a reliable feed is identified.",
      "accessed": "2026-04-23"
    }
  ],
  "youtubeChannels": [
    {
      "name": "Arenal / Lake Arenal on YouTube (search)",
      "url": "https://www.youtube.com/results?search_query=Arenal%20%2F%20Lake%20Arenal%20retirement%20expat%20living",
      "description": "YouTube search for channels covering retirement and expat life in Arenal / Lake Arenal. Replace with a specific channel once identified.",
      "accessed": "2026-04-23"
    }
  ],
  "bloggers": [
    {
      "name": "Arenal / Lake Arenal expat blogs (search)",
      "url": "https://www.google.com/search?q=Arenal%20%2F%20Lake%20Arenal%20expat%20retirement%20blog",
      "description": "Google search for English-language expat and retirement blogs about Arenal / Lake Arenal. Replace with a specific blog once identified.",
      "accessed": "2026-04-23"
    }
  ]
}
